[
  {
    "Id": "1496864",
    "ThreadId": "663154",
    "Html": "I wasn't sure where to post this so my apologies if this is the wrong place.  I want to thank you for your work on this project.  I have found this application very useful in several situations.  Please keep up the good work.\r<br />\n<br />\nI sent a small donation as well :)\r<br />\n<br />\nI encourage everyone else that finds it useful to do the same.  <br />\n",
    "PostedDate": "2017-06-01T19:07:15.367-07:00",
    "UserRole": null,
    "MarkedAsAnswerDate": null
  }
]